yclients/__init__.py
yclients/yclients.py
yclients_api-0.0.7.dist-info/LICENSE
yclients_api-0.0.7.dist-info/METADATA
yclients_api-0.0.7.dist-info/WHEEL
yclients_api-0.0.7.dist-info/top_level.txt
yclients_api-0.0.7.dist-info/RECORD
