Metadata-Version: 2.1
Name: yclients-api
Version: 0.0.7
Summary: Python YCLIENTS REST API wrapper on ujson and httpx
Home-page: https://github.com/CoolmixZero/yclients-api-python
Author: Nikita Shalashkov
Author-email: nikita.shalashkov@gmail.com
License: MIT
Project-URL: Bug Tracker, https://github.com/CoolmixZero/yclients-api-python/issues
Keywords: yclients,api,wrapper,python,httpx,ujson
Platform: any
Classifier: Intended Audience :: Developers
Classifier: License :: OSI Approved :: MIT License
Classifier: Operating System :: OS Independent
Classifier: Programming Language :: Python
Classifier: Programming Language :: Python :: 3.7
Classifier: Programming Language :: Python :: 3.8
Classifier: Programming Language :: Python :: 3.9
Classifier: Programming Language :: Python :: 3.10
Classifier: Programming Language :: Python :: 3.11
Classifier: Topic :: Software Development :: Libraries :: Python Modules
Requires-Python: >=3.7
License-File: LICENSE
